Metadata-Version: 2.1
Name: magma-cuda90
Version: 10.7.8
Summary: magma-cuda90 of magma-cuda90 of magma-cuda90
Home-page: UNKNOWN
Author: Aloneee walker
Author-email: aloneewalker@facebook.com
License: UNKNOWN
Platform: UNKNOWN
Classifier: Programming Language :: Python :: 3
Classifier: License :: OSI Approved :: MIT License
Classifier: Operating System :: OS Independent
